sit_calc/__init__.py
sit_calc/tax_dict.py
sit_calc_rileycworstell-0.0.1.dist-info/LICENSE
sit_calc_rileycworstell-0.0.1.dist-info/METADATA
sit_calc_rileycworstell-0.0.1.dist-info/WHEEL
sit_calc_rileycworstell-0.0.1.dist-info/top_level.txt
sit_calc_rileycworstell-0.0.1.dist-info/RECORD
