Metadata-Version: 2.1
Name: sit-calc-rileycworstell
Version: 0.0.1
Summary: Calculate income tax based on state
Home-page: https://github.com/rileyworstell/Python-State-Income-Tax
Author: Riley Worstell
Author-email: rcwors02@gmail.com
License: UNKNOWN
Platform: UNKNOWN
Classifier: Programming Language :: Python :: 3
Classifier: License :: OSI Approved :: MIT License
Classifier: Operating System :: OS Independent
Requires-Python: >=3.6
